LICENSE
MANIFEST.in
README
README.rst
README.upgrading.rst
RELEASE-NOTES.rst
setup.py
ssh_dispatch.py
django_anyvcs/__init__.py
django_anyvcs/admin.py
django_anyvcs/defaults.py
django_anyvcs/dispatch.py
django_anyvcs/models.py
django_anyvcs/remote.py
django_anyvcs/settings.py
django_anyvcs/shortcuts.py
django_anyvcs/tests.py
django_anyvcs/urls.py
django_anyvcs/views.py
django_anyvcs.egg-info/PKG-INFO
django_anyvcs.egg-info/SOURCES.txt
django_anyvcs.egg-info/dependency_links.txt
django_anyvcs.egg-info/entry_points.txt
django_anyvcs.egg-info/not-zip-safe
django_anyvcs.egg-info/requires.txt
django_anyvcs.egg-info/top_level.txt
django_anyvcs/migrations/0001_initial.py
django_anyvcs/migrations/0002_repo_disk_size.py
django_anyvcs/migrations/__init__.py
django_anyvcs/south_migrations/0001_initial.py
django_anyvcs/south_migrations/0002_auto__add_field_repo_public_read.py
django_anyvcs/south_migrations/0003_populate_field_repo_public_read.py
django_anyvcs/south_migrations/0004_auto__del_field_repo_public_rights.py
django_anyvcs/south_migrations/0005_auto__add_field_repo_disk_size.py
django_anyvcs/south_migrations/__init__.py