Metadata-Version: 1.1
Name: django-anyvcs
Version: 2.5.0
Summary: A Django app providing homogeneous management of VCS systems.
Home-page: https://github.com/ClemsonSoCUnix/django-anyvcs
Author: Scott Duckworth
Author-email: sduckwo@clemson.edu
License: BSD
Platform: UNKNOWN
Classifier: Environment :: Web Environment
Classifier: Framework :: Django
Classifier: Intended Audience :: Developers
Classifier: License :: OSI Approved :: BSD License
Classifier: Operating System :: OS Independent
Classifier: Programming Language :: Python
Classifier: Programming Language :: Python :: 2.7
Classifier: Programming Language :: Python :: 3.3
Classifier: Programming Language :: Python :: 3.4
Classifier: Topic :: Internet :: WWW/HTTP
Classifier: Topic :: Internet :: WWW/HTTP :: Dynamic Content
